laddr/__init__.py
laddr/llms.py
laddr/api/__init__.py
laddr/api/main.py
laddr/cli/__init__.py
laddr/cli/main.py
laddr/cli/commands/__init__.py
laddr/cli/commands/add.py
laddr/cli/commands/check.py
laddr/cli/commands/infra.py
laddr/cli/commands/init.py
laddr/cli/commands/management.py
laddr/cli/commands/prompt.py
laddr/cli/commands/run.py
laddr/cli/templates/Dockerfile.j2
laddr/cli/templates/README.md.j2
laddr/cli/templates/agent_flat.py.j2
laddr/cli/templates/docker-compose.yml.j2
laddr/cli/templates/dotenv.j2
laddr/cli/templates/main_flat.py.j2
laddr/cli/templates/requirements.txt.j2
laddr/cli/templates/tool.py.j2
laddr/cli/templates/tools_communication.py.j2
laddr/cli/templates/tools_web.py.j2
laddr/cli/utils/__init__.py
laddr/cli/utils/config.py
laddr/cli/utils/docker.py
laddr/cli/utils/errors.py
laddr/cli/utils/logger.py
laddr/cli/utils/templates.py
laddr/core/__init__.py
laddr/core/agent_runtime.py
laddr/core/cache.py
laddr/core/config.py
laddr/core/database.py
laddr/core/llm.py
laddr/core/mcp_client.py
laddr/core/message_bus.py
laddr/core/runtime_entry.py
laddr/core/storage.py
laddr/core/system_tools.py
laddr/core/tooling.py
laddr-0.8.2.dist-info/METADATA
laddr-0.8.2.dist-info/WHEEL
laddr-0.8.2.dist-info/entry_points.txt
laddr-0.8.2.dist-info/RECORD
