Metadata-Version: 2.4
Name: laddr
Version: 0.8.2
Summary: Laddr is a framework to build, run, and scale multi-agent systems that communicate, delegate, and execute tasks in parallel. Each agent can run multiple workers, powered by a queue-based delegation system that ensures horizontal scalability and resilience.
Project-URL: Homepage, https://laddr.dev
Project-URL: Documentation, https://docs.laddr.dev
Project-URL: Repository, https://github.com/laddr/laddr
Author-email: Laddr Team <nishant@agnetlabs.com>
Requires-Python: <3.14,>=3.10
Requires-Dist: click>=8.1.7
Requires-Dist: fastapi>=0.115.0
Requires-Dist: jinja2>=3.1.0
Requires-Dist: pydantic-settings>=2.10.1
Requires-Dist: pydantic>=2.11.9
Requires-Dist: python-dotenv>=1.1.1
Requires-Dist: pyyaml>=6.0.1
Requires-Dist: redis>=5.0.0
Requires-Dist: requests>=2.31.0
Requires-Dist: rich>=13.7.0
Requires-Dist: sqlalchemy>=2.0.0
Requires-Dist: uvicorn[standard]>=0.32.0
Provides-Extra: all
Requires-Dist: aio-pika>=9.4.0; extra == 'all'
Requires-Dist: aiokafka>=0.11.0; extra == 'all'
Requires-Dist: anthropic>=0.34.0; extra == 'all'
Requires-Dist: boto3>=1.34.0; extra == 'all'
Requires-Dist: google-generativeai>=0.8.0; extra == 'all'
Requires-Dist: groq>=0.11.0; extra == 'all'
Requires-Dist: minio>=7.2.0; extra == 'all'
Requires-Dist: openai>=1.13.3; extra == 'all'
Requires-Dist: psycopg2-binary>=2.9.0; extra == 'all'
Requires-Dist: pymysql>=1.1.0; extra == 'all'
Provides-Extra: all-dbs
Requires-Dist: psycopg2-binary>=2.9.0; extra == 'all-dbs'
Requires-Dist: pymysql>=1.1.0; extra == 'all-dbs'
Provides-Extra: all-llms
Requires-Dist: anthropic>=0.34.0; extra == 'all-llms'
Requires-Dist: google-generativeai>=0.8.0; extra == 'all-llms'
Requires-Dist: groq>=0.11.0; extra == 'all-llms'
Requires-Dist: openai>=1.13.3; extra == 'all-llms'
Provides-Extra: all-queues
Requires-Dist: aio-pika>=9.4.0; extra == 'all-queues'
Requires-Dist: aiokafka>=0.11.0; extra == 'all-queues'
Provides-Extra: all-storage
Requires-Dist: boto3>=1.34.0; extra == 'all-storage'
Requires-Dist: minio>=7.2.0; extra == 'all-storage'
Provides-Extra: anthropic
Requires-Dist: anthropic>=0.34.0; extra == 'anthropic'
Provides-Extra: dev
Requires-Dist: black>=24.0.0; extra == 'dev'
Requires-Dist: mypy>=1.11.0; extra == 'dev'
Requires-Dist: pytest-asyncio>=0.23.0; extra == 'dev'
Requires-Dist: pytest>=8.0.0; extra == 'dev'
Requires-Dist: ruff>=0.5.0; extra == 'dev'
Provides-Extra: gemini
Requires-Dist: google-generativeai>=0.8.0; extra == 'gemini'
Provides-Extra: groq
Requires-Dist: groq>=0.11.0; extra == 'groq'
Provides-Extra: kafka
Requires-Dist: aiokafka>=0.11.0; extra == 'kafka'
Provides-Extra: minio
Requires-Dist: minio>=7.2.0; extra == 'minio'
Provides-Extra: mysql
Requires-Dist: pymysql>=1.1.0; extra == 'mysql'
Provides-Extra: openai
Requires-Dist: openai>=1.13.3; extra == 'openai'
Provides-Extra: postgres
Requires-Dist: psycopg2-binary>=2.9.0; extra == 'postgres'
Provides-Extra: s3
Requires-Dist: boto3>=1.34.0; extra == 's3'
